qedit/__init__.py
qedit/__main__.py
qedit/cli.py
qedit/editor.py
qedit-0.2.0.dist-info/entry_points.txt
qedit-0.2.0.dist-info/METADATA
qedit-0.2.0.dist-info/WHEEL
qedit-0.2.0.dist-info/RECORD
